README.md
setup.cfg
setup.py
photoslocator.egg-info/PKG-INFO
photoslocator.egg-info/SOURCES.txt
photoslocator.egg-info/dependency_links.txt
photoslocator.egg-info/requires.txt
photoslocator.egg-info/top_level.txt
sample/__init__.py
sample/exif_data_utility.py
sample/photo_utils.py
sample/photoslocator