Metadata-Version: 2.1
Name: photoslocator
Version: 0.1.0
Summary: A simple tool to rename your photos using gps metadata
Home-page: https://github.com/DendoD96/photos_locator
Author: Daniele Rossi
Author-email: daniele.rossi27@unibo.it
License: GPLv3
Keywords: photography,gps-location
Platform: UNKNOWN
Classifier: Development Status :: 3 - Alpha
Classifier: Environment :: Console
Classifier: Intended Audience :: End Users/Desktop
Classifier: License :: OSI Approved :: GNU General Public License v3 (GPLv3)
Classifier: Topic :: Utilities
Classifier: Programming Language :: Python :: 3
Classifier: Programming Language :: Python :: 3.6
Classifier: Programming Language :: Python :: 3.7
Classifier: Programming Language :: Python :: 3.8
Classifier: Programming Language :: Python :: 3.9
